MANIFEST.in
README.rst
setup.py
zipf/__init__.py
zipf/__version__.py
zipf/zipf.py
zipf.egg-info/PKG-INFO
zipf.egg-info/SOURCES.txt
zipf.egg-info/dependency_links.txt
zipf.egg-info/requires.txt
zipf.egg-info/top_level.txt
zipf/cli/__init__.py
zipf/cli/cli.py
zipf/factories/__init__.py
zipf/factories/stop_words_en.json
zipf/factories/stop_words_it.json
zipf/factories/zipf_factory.py
zipf/factories/zipf_from_dir/__init__.py
zipf/factories/zipf_from_dir/cli_from_dir.py
zipf/factories/zipf_from_dir/statistic_from_dir.py
zipf/factories/zipf_from_dir/zipf_from_dir.py
zipf/factories/zipf_from_file/__init__.py
zipf/factories/zipf_from_file/zipf_from_file.py
zipf/factories/zipf_from_ksequence/__init__.py
zipf/factories/zipf_from_ksequence/zipf_from_ksequence.py
zipf/factories/zipf_from_list/__init__.py
zipf/factories/zipf_from_list/zipf_from_list.py
zipf/factories/zipf_from_text/__init__.py
zipf/factories/zipf_from_text/zipf_from_text.py
zipf/factories/zipf_from_url/__init__.py
zipf/factories/zipf_from_url/zipf_from_url.py
zipf/statistic/__init__.py
zipf/statistic/derivative.py
zipf/statistic/statistic.py