Metadata-Version: 1.1
Name: zipf
Version: 1.6.0
Summary: A package to create and work with zipf distributions
Home-page: https://github.com/LucaCappelletti94/zipf
Author: Luca Cappelletti
Author-email: cappelletti.luca94@gmail.com
License: MIT
Platform: UNKNOWN
Classifier: Development Status :: 5 - Production/Stable
Classifier: Intended Audience :: Information Technology
Classifier: Topic :: Scientific/Engineering :: Information Analysis
Classifier: License :: OSI Approved :: MIT License
Classifier: Programming Language :: Python :: 3
